[{"year":2021,"athletes":1175,"best":12.16,"top8_avg":12.42,"top50_avg":12.847,"median":14.61},{"year":2022,"athletes":1164,"best":12.35,"top8_avg":12.673,"top50_avg":13.077,"median":14.74},{"year":2023,"athletes":1500,"best":12.12,"top8_avg":12.534,"top50_avg":12.91,"median":14.83},{"year":2024,"athletes":1275,"best":12.17,"top8_avg":12.37,"top50_avg":12.789,"median":14.69},{"year":2025,"athletes":1322,"best":12.19,"top8_avg":12.346,"top50_avg":12.784,"median":14.73},{"year":2026,"athletes":1151,"best":12.46,"top8_avg":12.675,"top50_avg":13.104,"median":14.83}]